asiacell/__init__.py
asiacell/main.py
asiacell-0.0.8.dist-info/LICENSE
asiacell-0.0.8.dist-info/METADATA
asiacell-0.0.8.dist-info/WHEEL
asiacell-0.0.8.dist-info/top_level.txt
asiacell-0.0.8.dist-info/RECORD
