Metadata-Version: 2.1
Name: asiacell
Version: 0.0.8
Summary: A small example package
Home-page: https://github.com/alshbg1/asiacell
Author: ALSH
Author-email: author@example.com
Project-URL: Bug Tracker, https://github.com/pypa/sampleproject/issues
Classifier: Programming Language :: Python :: 3
Classifier: License :: OSI Approved :: MIT License
Classifier: Operating System :: OS Independent
Requires-Python: >=3.6
License-File: LICENSE
